neon_gui/__init__.py
neon_gui/__main__.py
neon_gui/cli.py
neon_gui/service.py
neon_gui/utils.py
neon_gui-1.4.0.dist-info/LICENSE.md
neon_gui-1.4.0.dist-info/METADATA
neon_gui-1.4.0.dist-info/WHEEL
neon_gui-1.4.0.dist-info/entry_points.txt
neon_gui-1.4.0.dist-info/top_level.txt
neon_gui-1.4.0.dist-info/RECORD
