Metadata-Version: 2.1
Name: neon-gui
Version: 1.4.0
Summary: Neon GUI Module
Home-page: https://github.com/NeonGeckoCom/neon_gui
Author: Neongecko
Author-email: developers@neon.ai
License: BSD-3-Clause
License-File: LICENSE.md
Requires-Dist: neon-utils[network]~=1.6
Requires-Dist: ovos-utils>=0.0.34,~=0.0
Requires-Dist: ovos-config>=0.0.10,~=0.0
Requires-Dist: click~=8.0
Requires-Dist: click-default-group~=1.2
Requires-Dist: tornado~=6.0
Requires-Dist: ovos-bus-client>=0.0.6,~=0.0
Requires-Dist: ovos-gui~=0.2
Provides-Extra: docker
Requires-Dist: ovos-gui-plugin-shell-companion~=1.0; extra == "docker"
Provides-Extra: test
Requires-Dist: pytest; extra == "test"
Requires-Dist: mock; extra == "test"
Requires-Dist: neon-messagebus~=2.0; extra == "test"
